{
  "app_list": [
    {
      "name": "WhatsApp",
      "img": "w.png",
      "show": "y",
      "working": "y",
      "update": "n"
    },
	{
      "name": "Bussiness",
      "img": "b.png",
      "show": "y",
      "working": "y",
      "update": "n"
    },
     {
      "name": "Reels",
      "img": "r.png",
      "show": "y",
      "working": "y",
      "update": "n"
    },
	{
      "name": "Instgram",
      "img": "i.png",
      "show": "y",
      "working": "y",
      "update": "n"
    },
	{
      "name": "Facebook",
      "img": "f.png",
      "show": "y",
      "working": "y",
      "update": "n"
    },
	{
      "name": "ShareChat",
      "img": "s.png",
      "show": "y",
      "working": "y",
      "update": "n"
    },
	{
      "name": "Linkedin",
      "img": "l.png",
      "show": "y",
      "working": "y",
      "update": "n"
    },
	{
      "name": "Pinterest",
      "img": "icon_pinterest.png",
      "show": "n",
      "working": "y",
      "update": "n"
    },
	{
      "name": "Threads",
      "img": "threads.png",
      "show": "n",
      "working": "y",
      "update": "n"
    }
  ]
}
